lscache_django/__init__.py
lscache_django/apps.py
lscache_django/conf.py
lscache_django/decorators.py
lscache_django/middleware.py
lscache_django/purging.py
lscache_django-0.2.3.dist-info/LICENSE
lscache_django-0.2.3.dist-info/METADATA
lscache_django-0.2.3.dist-info/WHEEL
lscache_django-0.2.3.dist-info/top_level.txt
lscache_django-0.2.3.dist-info/RECORD
