Metadata-Version: 2.2
Name: lscache-django
Version: 0.2.3
Summary: LiteSpeed Cache integration for Django
Author: Cold Egg
Project-URL: Homepage, https://github.com/litespeedtech/lscache-django
Project-URL: Documentation, https://github.com/litespeedtech/lscache-django/blob/main/README.md
Project-URL: Issues, https://github.com/litespeedtech/lscache-django/issues
Keywords: lscache,cache,django
Classifier: Framework :: Django
Classifier: Programming Language :: Python :: 3
Requires-Python: >=3.8
License-File: LICENSE
Requires-Dist: Django>=3.2
Requires-Dist: requests>=2.25
